goto/__init__.py
pygoto-1.0.2.dist-info/LICENSE
pygoto-1.0.2.dist-info/METADATA
pygoto-1.0.2.dist-info/WHEEL
pygoto-1.0.2.dist-info/top_level.txt
pygoto-1.0.2.dist-info/RECORD
