Metadata-Version: 2.1
Name: pygoto
Version: 1.0.2
Summary: Use goto in Python
Home-page: https://github.com/donno2048/pygoto
Author: Elisha Hollander
Author-email: just4now666666@gmail.com
License: MIT
Project-URL: Documentation, https://github.com/donno2048/pygoto#readme
Project-URL: Bug Reports, https://github.com/donno2048/pygoto/issues
Project-URL: Source Code, https://github.com/donno2048/pygoto
Platform: UNKNOWN
Classifier: Programming Language :: Python :: 3
Requires-Python: >=3.0
License-File: LICENSE
